[
	{
		"name": "天朝",
		"leaderName": "天子",
		"adjective": ["普天之下"],
		"style": "皆为王土",
		
		"startIntroPart1": "在将领与士兵之中，历史最辉煌的篇章莫过于此：那些从战场上凯旋而归的军队，曾多次经历战败与逆境，却始终坚韧不拔，最终成就了伟大的国家。尽管常常被敌人与竞争对手包围，但他们从未放弃。文学与艺术、文化与文明，这些世界中心的元素，在逆境中历久弥新。旋转肌，你将永恒地见证胜利与生命。",
		"startIntroPart2": "考验你的时刻，这座文明的基石能否支撑起你的建设？世界中心再次倒转，你是否能应对？一切秩序与和平的带来，你是否能见证帝国的再次崛起？倒转的荣耀，你是否能重新夺回，让人们再次转向你？",
		
		"declaringWar": "现在是时候偿还了。我知道你，你自己表现得非常糟糕。",
		"attacked": "我发誓！你很快就会后悔的！傻瓜！",
		"defeated": "胜利属于你，仁慈的上帝，你将获得希望。你的……是这一天。",
		"introduction": "勇敢的军人，你们是备受尊敬的，我们对你们怀有公正和公平的期望。",
		
		"neutralHello": "愿你平安。",
		"hateHello": "你想让我做什么？",
		"tradeRequest": "我与这笔交易有关，因为它存在的原因是，你已经做了那件事。",

		"outerColor": [110,110,110],
		"innerColor": [5,5,5],
		"uniqueName": "雷霆雨露，皆是天恩",
		"uniques": [
			"[+2 Culture, +1 Production, +1 Faith] from [{unimproved} {Bonus resource}] tiles [in all cities]", "[+1 Culture, +2 Production, +1 Faith] from [{improved} {Bonus resource}] tiles [in all cities]",
			"[+2 Culture, +1 Food, +1 Science] from [{unimproved} {Strategic resource}] tiles [in all cities]", "[+1 Culture, +2 Food, +1 Science] from [{improved} {Strategic resource}] tiles [in all cities]",
			"[+2 Culture, +2 Gold, +1 Happiness] from [{unimproved} {Luxury resource}] tiles [in all cities]", "[+1 Culture, +4 Gold, +1 Happiness] from [{improved} {Luxury resource}] tiles [in all cities]",
			"[+100]% Yield from every [Natural Wonder] <within [1] tiles of a [属地]>",
			"Cities are razed [3] times as fast", ],
		"cities": ["朝歌","长安","洛阳","顺天","应天","成都","晋阳","汴梁","余杭","奉天","广州","姑苏","成都","大理","河内","汉城","上海","天津","重庆","武汉","青岛","拉萨","大连","哈尔滨","长沙","南昌","南宁","兰州","呼和浩特","福州","台北","香港","乌鲁木齐","乌兰巴托","昆明","贵阳","宁波","深圳","银川","新郑","西宁","长春","厦门","济南","合肥","万象","仰光","海参崴","曼谷","曼德勒","西贡","平壤","海口","金边","石家庄","东京","京都"],
		"spyNames": ["天枢","天璇","天玑","天机","瑶光","玉衡","开阳","紫薇","破军","贪狼","七杀","文曲","武曲"]
	}
]
